{
    "code":200,
    "data":[{
      "cId":1,
      "cUserName":"张三",
      "idNumber":"1234567890865433222",
      "bankName":"如皋银行",
      "bankCode":"高航",
      "provinceNumber":"1234",
      "cityNumber":"1234",
      "lineNumber":1234,
      "branchName":"支行",
      "cardNumber":"122212121212121212121",
      "bindingPhone":"1929292929",
      "cardFront":"正面",
      "frontState":1,
      "cardReverse":"反面",
      "reverseState":1,
      "checkState":"1",
      "checkReason":"理由",
      "useState":"0",
      "creationTime":"2017-9-9",
      "alterTime":"2017-9-9"
    },{
      "cId":2,
      "cUserName":"张三",
      "idNumber":"1234567890865433222",
      "bankName":"如皋银行",
      "bankCode":"高航",
      "provinceNumber":"1234",
      "cityNumber":"1234",
      "lineNumber":1234,
      "branchName":"支行",
      "cardNumber":"122212121212121212121",
      "bindingPhone":"1929292929",
      "cardFront":"正面",
      "frontState":1,
      "cardReverse":"反面",
      "reverseState":1,
      "checkState":"1",
      "checkReason":"理由",
      "useState":"0",
      "creationTime":"2017-9-9",
      "alterTime":"2017-9-9"
    },{
      "cId":2,
      "cUserName":"张三",
      "idNumber":"1234567890865433222",
      "bankName":"如皋银行",
      "bankCode":"高航",
      "provinceNumber":"1234",
      "cityNumber":"1234",
      "lineNumber":1234,
      "branchName":"支行",
      "cardNumber":"122212121212121212121",
      "bindingPhone":"1929292929",
      "cardFront":"正面",
      "frontState":1,
      "cardReverse":"反面",
      "reverseState":1,
      "checkState":"1",
      "checkReason":"理由",
      "useState":"0",
      "creationTime":"2017-9-9",
      "alterTime":"2017-9-9"
    },{
      "cId":2,
      "cUserName":"张三",
      "idNumber":"1234567890865433222",
      "bankName":"如皋银行",
      "bankCode":"高航",
      "provinceNumber":"1234",
      "cityNumber":"1234",
      "lineNumber":1234,
      "branchName":"支行",
      "cardNumber":"122212121212121212121",
      "bindingPhone":"1929292929",
      "cardFront":"正面",
      "frontState":1,
      "cardReverse":"反面",
      "reverseState":1,
      "checkState":"1",
      "checkReason":"理由",
      "useState":"0",
      "creationTime":"2017-9-9",
      "alterTime":"2017-9-9"
    },{
      "cId":2,
      "cUserName":"张三",
      "idNumber":"1234567890865433222",
      "bankName":"如皋银行",
      "bankCode":"高航",
      "provinceNumber":"1234",
      "cityNumber":"1234",
      "lineNumber":1234,
      "branchName":"支行",
      "cardNumber":"122212121212121212121",
      "bindingPhone":"1929292929",
      "cardFront":"正面",
      "frontState":1,
      "cardReverse":"反面",
      "reverseState":1,
      "checkState":"1",
      "checkReason":"理由",
      "useState":"0",
      "creationTime":"2017-9-9",
      "alterTime":"2017-9-9"
    },{
      "cId":2,
      "cUserName":"张三",
      "idNumber":"1234567890865433222",
      "bankName":"如皋银行",
      "bankCode":"高航",
      "provinceNumber":"1234",
      "cityNumber":"1234",
      "lineNumber":1234,
      "branchName":"支行",
      "cardNumber":"122212121212121212121",
      "bindingPhone":"1929292929",
      "cardFront":"正面",
      "frontState":1,
      "cardReverse":"反面",
      "reverseState":1,
      "checkState":"1",
      "checkReason":"理由",
      "useState":"0",
      "creationTime":"2017-9-9",
      "alterTime":"2017-9-9"
    }]
}